contb/__init__.py
contb/calcular_balanco.py
contb/calcular_rescisao.py
contb/exportar_pdf.py
contb/grafico.py
contb/registrar_transacao.py
contb-0.0.3.dist-info/METADATA
contb-0.0.3.dist-info/WHEEL
contb-0.0.3.dist-info/top_level.txt
contb-0.0.3.dist-info/RECORD
